odoo/addons/l10n_ro_dvi/README.rst
odoo/addons/l10n_ro_dvi/__init__.py
odoo/addons/l10n_ro_dvi/__manifest__.py
odoo/addons/l10n_ro_dvi/doc/DVI.docx
odoo/addons/l10n_ro_dvi/i18n/l10n_ro_dvi.pot
odoo/addons/l10n_ro_dvi/i18n/ro.po
odoo/addons/l10n_ro_dvi/models/__init__.py
odoo/addons/l10n_ro_dvi/models/account_invoice.py
odoo/addons/l10n_ro_dvi/models/l10n_ro_account_dvi.py
odoo/addons/l10n_ro_dvi/models/res_company.py
odoo/addons/l10n_ro_dvi/models/stock_landed_cost.py
odoo/addons/l10n_ro_dvi/readme/CONTRIBUTORS.md
odoo/addons/l10n_ro_dvi/readme/DESCRIPTION.md
odoo/addons/l10n_ro_dvi/readme/USAGE.md
odoo/addons/l10n_ro_dvi/security/ir.model.access.csv
odoo/addons/l10n_ro_dvi/static/description/icon.png
odoo/addons/l10n_ro_dvi/static/description/icon.svg
odoo/addons/l10n_ro_dvi/static/description/index.html
odoo/addons/l10n_ro_dvi/tests/__init__.py
odoo/addons/l10n_ro_dvi/tests/test_dvi.py
odoo/addons/l10n_ro_dvi/views/account_dvi_view.xml
odoo/addons/l10n_ro_dvi/views/account_invoice_view.xml
odoo/addons/l10n_ro_dvi/views/stock_landed_cost_view.xml
odoo_addon_l10n_ro_dvi-19.0.0.0.0.7.dist-info/METADATA
odoo_addon_l10n_ro_dvi-19.0.0.0.0.7.dist-info/WHEEL
odoo_addon_l10n_ro_dvi-19.0.0.0.0.7.dist-info/top_level.txt
odoo_addon_l10n_ro_dvi-19.0.0.0.0.7.dist-info/RECORD
